domovoi/__init__.py
domovoi/app.py
domovoi/default_iam_policy.json
domovoi/examples/alb-event.json
domovoi/examples/alexa-event.json
domovoi/examples/apigateway-event.json
domovoi/examples/cloudformation-event.json
domovoi/examples/cloudfront-event.json
domovoi/examples/cloudtrail-event.json
domovoi/examples/cloudwatch-event.json
domovoi/examples/codecommit-event.json
domovoi/examples/cognito-event.json
domovoi/examples/config-event.json
domovoi/examples/dynamodb-event.json
domovoi/examples/firehose-event.json
domovoi/examples/kinesis-event.json
domovoi/examples/logs-event.json
domovoi/examples/s3-event.json
domovoi/examples/ses-event.json
domovoi/examples/sns-event.json
domovoi/examples/sqs-event.json
domovoi-2.0.2.data/scripts/domovoi
domovoi-2.0.2.dist-info/LICENSE
domovoi-2.0.2.dist-info/METADATA
domovoi-2.0.2.dist-info/WHEEL
domovoi-2.0.2.dist-info/top_level.txt
domovoi-2.0.2.dist-info/RECORD
