Metadata-Version: 2.1
Name: domovoi
Version: 2.0.2
Summary: AWS Lambda event handler manager
Home-page: https://github.com/kislyuk/domovoi
Author: Andrey Kislyuk
Author-email: kislyuk@gmail.com
License: Apache Software License
Platform: MacOS X
Platform: Posix
Classifier: Intended Audience :: Developers
Classifier: License :: OSI Approved :: Apache Software License
Classifier: Operating System :: MacOS :: MacOS X
Classifier: Operating System :: POSIX
Classifier: Programming Language :: Python
Classifier: Programming Language :: Python :: 2.7
Classifier: Programming Language :: Python :: 3.3
Classifier: Programming Language :: Python :: 3.4
Classifier: Programming Language :: Python :: 3.5
Classifier: Topic :: Software Development :: Libraries :: Python Modules
Requires-Dist: boto3 (<2,>=1.7.19)
Requires-Dist: chalice (<2,>=1.3.0)
Requires-Dist: enum34 (<2,>=1.1.6) ; python_version == "2.7"
